Metadata-Version: 1.1
Name: RBTHSC
Version: 0.7.9.2.dev0
Summary: Command line tools for use with Review Board
Home-page: http://www.reviewboard.org/
Author: Christian Hammond
Author-email: chipx86@chipx86.com
License: MIT
Download-URL: http://downloads.reviewboard.org/releases/RBTHSC/0.7/
Platform: UNKNOWN
Classifier: Development Status :: 4 - Beta
Classifier: Environment :: Console
Classifier: Intended Audience :: Developers
Classifier: License :: OSI Approved :: MIT License
Classifier: Operating System :: OS Independent
Classifier: Programming Language :: Python
Classifier: Topic :: Software Development
